odoo/addons/product_net_weight/README.rst
odoo/addons/product_net_weight/__init__.py
odoo/addons/product_net_weight/__manifest__.py
odoo/addons/product_net_weight/demo/product_product.xml
odoo/addons/product_net_weight/i18n/fr.po
odoo/addons/product_net_weight/i18n/it.po
odoo/addons/product_net_weight/i18n/product_net_weight.pot
odoo/addons/product_net_weight/models/__init__.py
odoo/addons/product_net_weight/models/product_product.py
odoo/addons/product_net_weight/models/product_template.py
odoo/addons/product_net_weight/readme/CONTRIBUTORS.rst
odoo/addons/product_net_weight/readme/DESCRIPTION.rst
odoo/addons/product_net_weight/readme/ROADMAP.rst
odoo/addons/product_net_weight/readme/USAGE.rst
odoo/addons/product_net_weight/static/description/icon.png
odoo/addons/product_net_weight/static/description/index.html
odoo/addons/product_net_weight/static/description/product_form.png
odoo/addons/product_net_weight/views/view_product_product.xml
odoo/addons/product_net_weight/views/view_product_template.xml
odoo13_addon_product_net_weight-13.0.1.0.1.dev6.dist-info/METADATA
odoo13_addon_product_net_weight-13.0.1.0.1.dev6.dist-info/WHEEL
odoo13_addon_product_net_weight-13.0.1.0.1.dev6.dist-info/top_level.txt
odoo13_addon_product_net_weight-13.0.1.0.1.dev6.dist-info/RECORD
